.gitignore
CHANGES.txt
MANIFEST.in
README.rst
bootstrap.py
buildout.cfg
setup.py
collective/__init__.py
collective.galleria.egg-info/PKG-INFO
collective.galleria.egg-info/SOURCES.txt
collective.galleria.egg-info/dependency_links.txt
collective.galleria.egg-info/entry_points.txt
collective.galleria.egg-info/namespace_packages.txt
collective.galleria.egg-info/not-zip-safe
collective.galleria.egg-info/requires.txt
collective.galleria.egg-info/top_level.txt
collective/galleria/__init__.py
collective/galleria/configure.zcml
collective/galleria/i18n.py
collective/galleria/rebuild_i18n.sh
collective/galleria/tests.py
collective/galleria/browser/__init__.py
collective/galleria/browser/configure.zcml
collective/galleria/browser/galleria.pt
collective/galleria/browser/galleria.py
collective/galleria/interfaces/__init__.py
collective/galleria/interfaces/gallerialayerlayer.py
collective/galleria/interfaces/settings.py
collective/galleria/locales/collective.galleria.pot
collective/galleria/locales/fr/LC_MESSAGES/collective.galleria.po
collective/galleria/profiles/default/browserlayer.xml
collective/galleria/profiles/default/jsregistry.xml
collective/galleria/profiles/default/metadata.xml
collective/galleria/profiles/default/registry.xml
collective/galleria/profiles/default/types/Folder.xml
collective/galleria/profiles/default/types/Link.xml
collective/galleria/profiles/default/types/Topic.xml
collective/galleria/upgrades/__init__.py
collective/galleria/upgrades/configure.zcml
collective/galleria/upgrades/v10xx.py
docs/INSTALL.txt
docs/LICENSE.GPL
docs/LICENSE.txt