Metadata-Version: 1.0
Name: collective.galleria
Version: 1.2.1
Summary: Galleria integration into Plone
Home-page: https://github.com/collective/collective.galleria
Author: JeanMichel FRANCOIS aka toutpt
Author-email: toutpt@gmail.com
License: GPL
Platform: UNKNOWN
Classifier: Framework :: Plone
Classifier: Programming Language :: Python
